test/__init__.py
test/test_Sample.py
test/test_functions.py
transmission/__init__.py
transmission/cli_tools.py
transmission/transmission.py
transmission_popgen-0.0.10.dist-info/LICENSE
transmission_popgen-0.0.10.dist-info/METADATA
transmission_popgen-0.0.10.dist-info/WHEEL
transmission_popgen-0.0.10.dist-info/entry_points.txt
transmission_popgen-0.0.10.dist-info/top_level.txt
transmission_popgen-0.0.10.dist-info/RECORD
